httpx_oauth2/__init__.py
httpx_oauth2/_interfaces.py
httpx_oauth2/_model.py
httpx_oauth2/_oauth_authority_client.py
httpx_oauth2/_token.py
httpx_oauth2/_token_provider.py
httpx_oauth2/_transport.py
httpx_oauth2/py.typed
httpx_oauth2-1.0.5.dist-info/METADATA
httpx_oauth2-1.0.5.dist-info/WHEEL
httpx_oauth2-1.0.5.dist-info/licenses/LICENSE.md
httpx_oauth2-1.0.5.dist-info/RECORD
