Metadata-Version: 2.4
Name: httpx-oauth2
Version: 1.0.5
Summary: Add your description here
Author-email: Bastien Exertier <exertier.bastien@gmail.com>
License-File: LICENSE.md
Requires-Python: >=3.10
Requires-Dist: cachelib>=0.13.0
Requires-Dist: httpx>=0.28.1
Requires-Dist: jwt>=1.3.1
